MakeParallel.py
make_parallel_decorator-0.0.1.dist-info/LICENSE.txt
make_parallel_decorator-0.0.1.dist-info/METADATA
make_parallel_decorator-0.0.1.dist-info/WHEEL
make_parallel_decorator-0.0.1.dist-info/top_level.txt
make_parallel_decorator-0.0.1.dist-info/RECORD
