Metadata-Version: 2.1
Name: make-parallel-decorator
Version: 0.0.1
Summary: This is a decorator that can be used to convert a normal function into multi threaded
Home-page: UNKNOWN
Author: UNKNOWN
Author-email: UNKNOWN
License: UNKNOWN
Platform: UNKNOWN
